[
  {
    "lang_id": 1,
    "grade_id": 11,
    "book_id": "1022",
    "title_raw": " Civic Education  -   New Syllabus",
    "chapter_url_list": [
      "http://www.edupub.gov.lk/Administrator/English/11/civic G11E/book.pdf"
    ]
  },
  {
    "lang_id": 1,
    "grade_id": 10,
    "book_id": "1085",
    "title_raw": " Mathematics Part II -   New Syllabus",
    "chapter_url_list": [
      "http://www.edupub.gov.lk/Administrator/English/10/maths G-10 P-II E/maths P-II G-10 E.pdf"
    ]
  },
  {
    "lang_id": 1,
    "grade_id": 11,
    "book_id": "1230",
    "title_raw": " English Pupils Book  -    New syllsbus",
    "chapter_url_list": [
      "http://www.edupub.gov.lk/Administrator/English/11/english PB G-11/book.pdf"
    ]
  },
  {
    "lang_id": 1,
    "grade_id": 10,
    "book_id": "1253",
    "title_raw": " Science Part II  -    New Syllabus",
    "chapter_url_list": [
      "http://www.edupub.gov.lk/Administrator/English/10/science G-10 P-II E/science G-10 P-II E.pdf"
    ]
  },
  {
    "lang_id": 1,
    "grade_id": 11,
    "book_id": "1282",
    "title_raw": " Geography  -   New Syllabus",
    "chapter_url_list": [
      "http://www.edupub.gov.lk/Administrator/English/11/geo G-11 E/geography G-11 E.pdf"
    ]
  },
  {
    "lang_id": 1,
    "grade_id": 10,
    "book_id": "1328",
    "title_raw": " Information Communication Technology  -    New Syllabus",
    "chapter_url_list": [
      "http://www.edupub.gov.lk/Administrator/English/10/ict G-10 E/ICT G-10 E.pdf"
    ]
  },
  {
    "lang_id": 1,
    "grade_id": 10,
    "book_id": "1329",
    "title_raw": " Business & Accounting Studies -    New Syllabus",
    "chapter_url_list": [
      "http://www.edupub.gov.lk/Administrator/English/10/business St G-10 E/Business and Accounting Studies_G10(E).pdf"
    ]
  },
  {
    "lang_id": 1,
    "grade_id": 9,
    "book_id": "1331",
    "title_raw": " Information and Communication Technology - Work book  -   New Syllabus",
    "chapter_url_list": [
      "http://www.edupub.gov.lk/Administrator/English/9/ict G-9 E WB/ICT G-9 E WB.pdf"
    ]
  },
  {
    "lang_id": 1,
    "grade_id": 9,
    "book_id": "1333",
    "title_raw": " Mathematics  Part  III  - New Syllabus  ",
    "chapter_url_list": [
      "http://www.edupub.gov.lk/Administrator/English/9/maths G-9 P-III E/maths G-9 P-III E.pdf"
    ]
  },
  {
    "lang_id": 1,
    "grade_id": 11,
    "book_id": "1334",
    "title_raw": " Science Part I  -  New Syllabus",
    "chapter_url_list": [
      "http://www.edupub.gov.lk/Administrator/English/11/science G-11 P-I E/science G-11 P-I E.pdf"
    ]
  },
  {
    "lang_id": 1,
    "grade_id": 9,
    "book_id": "1335",
    "title_raw": " Science  Part  II  -   New Syllabus  ",
    "chapter_url_list": [
      "http://www.edupub.gov.lk/Administrator/English/9/science G-9 P-II E/Science Part II English G-9.pdf"
    ]
  },
  {
    "lang_id": 1,
    "grade_id": 10,
    "book_id": "1336",
    "title_raw": " Science Part I  -    New Syllabus",
    "chapter_url_list": [
      "http://www.edupub.gov.lk/Administrator/English/10/science G-10 P-I E/science G-10 P-I E.pdf"
    ]
  },
  {
    "lang_id": 1,
    "grade_id": 11,
    "book_id": "1339",
    "title_raw": " Science Part II -  New Syllabus",
    "chapter_url_list": [
      "http://www.edupub.gov.lk/Administrator/English/11/science G-11 P-II E/science G-11  P-II E.pdf"
    ]
  },
  {
    "lang_id": 1,
    "grade_id": 11,
    "book_id": "1341",
    "title_raw": " Information and Communication Technology  -  New Syllabus",
    "chapter_url_list": [
      "http://www.edupub.gov.lk/Administrator/English/11/ICT G-11 E/ICT G-11 E.pdf"
    ]
  },
  {
    "lang_id": 1,
    "grade_id": 9,
    "book_id": "1343",
    "title_raw": " Civic Education  -  New Syllabus  ",
    "chapter_url_list": [
      "http://www.edupub.gov.lk/Administrator/English/9/civic G-9 E/civic G-9 E.pdf"
    ]
  },
  {
    "lang_id": 1,
    "grade_id": 10,
    "book_id": "1344",
    "title_raw": " Civic Education -   New Syllabus",
    "chapter_url_list": [
      "http://www.edupub.gov.lk/Administrator/English/10/civic G-10 E/civic G-10 E.pdf"
    ]
  },
  {
    "lang_id": 1,
    "grade_id": 9,
    "book_id": "1345",
    "title_raw": " Geography   -     New Syllabus",
    "chapter_url_list": [
      "http://www.edupub.gov.lk/Administrator/English/9/geo G-9 E/geo G-9 E.pdf"
    ]
  },
  {
    "lang_id": 1,
    "grade_id": 10,
    "book_id": "1346",
    "title_raw": " Geography  -   New Syllabus",
    "chapter_url_list": [
      "http://www.edupub.gov.lk/Administrator/English/10/geo G-10 E/geo G-10 E.pdf"
    ]
  },
  {
    "lang_id": 1,
    "grade_id": 11,
    "book_id": "1356",
    "title_raw": " Entrepreneurial Studies -   New Syllabus",
    "chapter_url_list": [
      "http://www.edupub.gov.lk/Administrator/English/11/entrepreG-11 E/entrep G-11 E.pdf"
    ]
  },
  {
    "lang_id": 1,
    "grade_id": 11,
    "book_id": "1369",
    "title_raw": " Business & Accounting Studies -  New Syllabus",
    "chapter_url_list": [
      "http://www.edupub.gov.lk/Administrator/English/11/business St G-11 E/business G-11 E.pdf"
    ]
  },
  {
    "lang_id": 1,
    "grade_id": 9,
    "book_id": "1370",
    "title_raw": " Mathematics  Part  I  - New Syllabus  ",
    "chapter_url_list": [
      "http://www.edupub.gov.lk/Administrator/English/9/maths G-9 P-I E/maths G-9 P- IE.pdf"
    ]
  },
  {
    "lang_id": 1,
    "grade_id": 11,
    "book_id": "1380",
    "title_raw": " Health & Physical Education \u2013  new Syllabus    ",
    "chapter_url_list": [
      "http://www.edupub.gov.lk/Administrator/English/11/health G-11 E/Health & physical G-11- Inner_V3.pdf"
    ]
  },
  {
    "lang_id": 1,
    "grade_id": 9,
    "book_id": "1412",
    "title_raw": " Mathematics  Part  II  - New Syllabus  ",
    "chapter_url_list": [
      "http://www.edupub.gov.lk/Administrator/English/9/maths G-9 P-II S/maths G9 P-II E.pdf"
    ]
  },
  {
    "lang_id": 1,
    "grade_id": 9,
    "book_id": "1414",
    "title_raw": " Science  Part  I  -   New Syllabus  ",
    "chapter_url_list": [
      "http://www.edupub.gov.lk/Administrator/English/9/science G-9 P-I E/science G-9 P-I E.pdf"
    ]
  },
  {
    "lang_id": 1,
    "grade_id": 9,
    "book_id": "1560",
    "title_raw": " English Pupils Book  -  New Syllabus",
    "chapter_url_list": [
      "http://www.edupub.gov.lk/Administrator/English/9/en pb g-9/english pb G-9.pdf"
    ]
  },
  {
    "lang_id": 1,
    "grade_id": 11,
    "book_id": "1561",
    "title_raw": " English work book  -   New syllabus",
    "chapter_url_list": [
      "http://www.edupub.gov.lk/Administrator/English/11/en wb g-11/english WBg-11.pdf"
    ]
  },
  {
    "lang_id": 1,
    "grade_id": 10,
    "book_id": "1570",
    "title_raw": " English Literary Appreciation  -   New Syllabus ",
    "chapter_url_list": [
      "http://www.edupub.gov.lk/Administrator/English/10/en ap g-10/English Literary texts.pdf"
    ]
  },
  {
    "lang_id": 1,
    "grade_id": 9,
    "book_id": "1576",
    "title_raw": " English Workbook  -   New Syllabus",
    "chapter_url_list": [
      "http://www.edupub.gov.lk/Administrator/English/9/en wb g-9/en wb g-9.pdf"
    ]
  },
  {
    "lang_id": 1,
    "grade_id": 10,
    "book_id": "1578",
    "title_raw": " Mathematics Part 1  -    New Syllabus",
    "chapter_url_list": [
      "http://www.edupub.gov.lk/Administrator/English/10/maths g-10 p-I s/maths g-10 p-I E.pdf"
    ]
  },
  {
    "lang_id": 1,
    "grade_id": 11,
    "book_id": "1580",
    "title_raw": " Mathematics Part I -  New Syllabus",
    "chapter_url_list": [
      "http://www.edupub.gov.lk/Administrator/English/11/maths g-11 p-I E/maths g-11 p-I E.pdf"
    ]
  },
  {
    "lang_id": 1,
    "grade_id": 11,
    "book_id": "1583",
    "title_raw": " Mathematics Part II -  New Syllabus",
    "chapter_url_list": [
      "http://www.edupub.gov.lk/Administrator/English/11/maths g-11 p-II E/maths g-11 p-II E.pdf"
    ]
  },
  {
    "lang_id": 1,
    "grade_id": 11,
    "book_id": "1588",
    "title_raw": " Mathematics Part III -  New Syllabus",
    "chapter_url_list": [
      "http://www.edupub.gov.lk/Administrator/English/11/maths g-11 p-III E/maths g-11 p-III E.pdf"
    ]
  },
  {
    "lang_id": 1,
    "grade_id": 9,
    "book_id": "1766",
    "title_raw": " History",
    "chapter_url_list": [
      "http://www.edupub.gov.lk/Administrator/English/9/history g9 E/history G-9 E.pdf"
    ]
  },
  {
    "lang_id": 1,
    "grade_id": 10,
    "book_id": "1767",
    "title_raw": " History",
    "chapter_url_list": [
      "http://www.edupub.gov.lk/Administrator/English/10/history 10 E/histoy G-10 E.pdf"
    ]
  },
  {
    "lang_id": 1,
    "grade_id": 11,
    "book_id": "1768",
    "title_raw": " History",
    "chapter_url_list": [
      "http://www.edupub.gov.lk/Administrator/English/11/history 11 E/history G-11 E.pdf"
    ]
  },
  {
    "lang_id": 1,
    "grade_id": 10,
    "book_id": "1770",
    "title_raw": " Catholicism",
    "chapter_url_list": [
      "http://www.edupub.gov.lk/Administrator/English/10/Catholicism 10 E/katholika G-10 E.pdf"
    ]
  },
  {
    "lang_id": 1,
    "grade_id": 11,
    "book_id": "1771",
    "title_raw": " Catholicism",
    "chapter_url_list": [
      "http://www.edupub.gov.lk/Administrator/English/11/Catholicism 11 E/katholika G-11 E.pdf"
    ]
  },
  {
    "lang_id": 1,
    "grade_id": 9,
    "book_id": "1774",
    "title_raw": " Catholicism",
    "chapter_url_list": [
      "http://www.edupub.gov.lk/Administrator/English/9/Catholicism G-9 E/catholicism G-9.pdf"
    ]
  },
  {
    "lang_id": 1,
    "grade_id": 10,
    "book_id": "642",
    "title_raw": " Entrepreneurship Education  -    New Syllabus",
    "chapter_url_list": [
      "http://www.edupub.gov.lk/Administrator/English/10/Entrepreneurial Studies G-10 E/Chapter 01 - E.pdf",
      "http://www.edupub.gov.lk/Administrator/English/10/Entrepreneurial Studies G-10 E/Chapter 02 - E.pdf",
      "http://www.edupub.gov.lk/Administrator/English/10/Entrepreneurial Studies G-10 E/Chapter 03 - E.pdf",
      "http://www.edupub.gov.lk/Administrator/English/10/Entrepreneurial Studies G-10 E/Chapter 04 - E.pdf",
      "http://www.edupub.gov.lk/Administrator/English/10/Entrepreneurial Studies G-10 E/Chapter 05 - E.pdf",
      "http://www.edupub.gov.lk/Administrator/English/10/Entrepreneurial Studies G-10 E/Chapter 06 - E.pdf",
      "http://www.edupub.gov.lk/Administrator/English/10/Entrepreneurial Studies G-10 E/Chapter 07 - E.pdf"
    ]
  },
  {
    "lang_id": 1,
    "grade_id": 10,
    "book_id": "650",
    "title_raw": " English Pupils Book -  New Syllabus",
    "chapter_url_list": [
      "http://www.edupub.gov.lk/Administrator/English/10/English Pupils Book G 10 - E/Unit 1 pdf People.pdf",
      "http://www.edupub.gov.lk/Administrator/English/10/English Pupils Book G 10 - E/Unit 2 pdf ok on your way.pdf",
      "http://www.edupub.gov.lk/Administrator/English/10/English Pupils Book G 10 - E/Unit 3 Travel.pdf",
      "http://www.edupub.gov.lk/Administrator/English/10/English Pupils Book G 10 - E/Unit 4 Lets talk.pdf",
      "http://www.edupub.gov.lk/Administrator/English/10/English Pupils Book G 10 - E/Unit 5 Best Practices.pdf",
      "http://www.edupub.gov.lk/Administrator/English/10/English Pupils Book G 10 - E/Unit 6 Information.pdf",
      "http://www.edupub.gov.lk/Administrator/English/10/English Pupils Book G 10 - E/Unit 7 Learning is fun.pdf",
      "http://www.edupub.gov.lk/Administrator/English/10/English Pupils Book G 10 - E/Unit 8 Healthy Food.pdf",
      "http://www.edupub.gov.lk/Administrator/English/10/English Pupils Book G 10 - E/Unit 9 Nature.pdf",
      "http://www.edupub.gov.lk/Administrator/English/10/English Pupils Book G 10 - E/Unit 10 Personality.pdf",
      "http://www.edupub.gov.lk/Administrator/English/10/English Pupils Book G 10 - E/Unit 11 The right career.pdf",
      "http://www.edupub.gov.lk/Administrator/English/10/English Pupils Book G 10 - E/Unit 12 Success.pdf",
      "http://www.edupub.gov.lk/Administrator/English/10/English Pupils Book G 10 - E/Unit 13 Future.pdf",
      "http://www.edupub.gov.lk/Administrator/English/10/English Pupils Book G 10 - E/Unit 14 Sports.pdf"
    ]
  },
  {
    "lang_id": 1,
    "grade_id": 10,
    "book_id": "653",
    "title_raw": " Health and Physical Education -    New Syllabus",
    "chapter_url_list": [
      "http://www.edupub.gov.lk/Administrator/English/10/Health & physical Education G 10 - E/chap - 1.pdf",
      "http://www.edupub.gov.lk/Administrator/English/10/Health & physical Education G 10 - E/chap -2.pdf",
      "http://www.edupub.gov.lk/Administrator/English/10/Health & physical Education G 10 - E/chap 3.pdf",
      "http://www.edupub.gov.lk/Administrator/English/10/Health & physical Education G 10 - E/chap 4.pdf",
      "http://www.edupub.gov.lk/Administrator/English/10/Health & physical Education G 10 - E/chap 5.pdf",
      "http://www.edupub.gov.lk/Administrator/English/10/Health & physical Education G 10 - E/Chap 6 new.pdf",
      "http://www.edupub.gov.lk/Administrator/English/10/Health & physical Education G 10 - E/Chp 7.pdf",
      "http://www.edupub.gov.lk/Administrator/English/10/Health & physical Education G 10 - E/chap 8 new.pdf",
      "http://www.edupub.gov.lk/Administrator/English/10/Health & physical Education G 10 - E/chp 9.pdf",
      "http://www.edupub.gov.lk/Administrator/English/10/Health & physical Education G 10 - E/chap - 10 new.pdf"
    ]
  },
  {
    "lang_id": 1,
    "grade_id": 10,
    "book_id": "667",
    "title_raw": " English Work Book -   New Syllbus",
    "chapter_url_list": [
      "http://www.edupub.gov.lk/Administrator/English/10/English Work Book G 10 E/english WB G-10.pdf"
    ]
  },
  {
    "lang_id": 1,
    "grade_id": 9,
    "book_id": "972",
    "title_raw": " Health and Physical Education  - New Syllabus  ",
    "chapter_url_list": [
      "http://www.edupub.gov.lk/Administrator/English/9/health G9 E/health G9 E.pdf"
    ]
  }
]